CHANGES.rst
DESCRIPTION.rst
LICENSE
MANIFEST.in
README.md
setup.py
src/wai/common/_ClassRegistry.py
src/wai/common/_Interval.py
src/wai/common/_InvalidStateError.py
src/wai/common/_TwoWayDict.py
src/wai/common/__init__.py
src/wai/common/_functions.py
src/wai/common/_memoise.py
src/wai/common/_pool.py
src/wai/common/_switch.py
src/wai/common/_typing.py
src/wai/common/onehot.py
src/wai/common/abc/__init__.py
src/wai/common/abc/_functions.py
src/wai/common/abc/constants.py
src/wai/common/adams/__init__.py
src/wai/common/adams/imaging/__init__.py
src/wai/common/adams/imaging/locateobjects/_LocatedObject.py
src/wai/common/adams/imaging/locateobjects/_LocatedObjects.py
src/wai/common/adams/imaging/locateobjects/_NormalizedLocatedObject.py
src/wai/common/adams/imaging/locateobjects/_NormalizedLocatedObjects.py
src/wai/common/adams/imaging/locateobjects/__init__.py
src/wai/common/adams/imaging/locateobjects/_convert.py
src/wai/common/adams/imaging/locateobjects/constants.py
src/wai/common/cli/_ArgumentParserConfigurer.py
src/wai/common/cli/_CLIFactory.py
src/wai/common/cli/_CLIInstantiable.py
src/wai/common/cli/_CLIRepresentable.py
src/wai/common/cli/_OptionHandler.py
src/wai/common/cli/_OptionValueHandler.py
src/wai/common/cli/__init__.py
src/wai/common/cli/_typing.py
src/wai/common/cli/constants.py
src/wai/common/cli/context/_OptionClassContext.py
src/wai/common/cli/context/_OptionContext.py
src/wai/common/cli/context/_OptionInstanceContext.py
src/wai/common/cli/context/__init__.py
src/wai/common/cli/options/_ClassOption.py
src/wai/common/cli/options/_CountOption.py
src/wai/common/cli/options/_FlagOption.py
src/wai/common/cli/options/_Option.py
src/wai/common/cli/options/_TypedOption.py
src/wai/common/cli/options/__init__.py
src/wai/common/cli/util/_ConcatAction.py
src/wai/common/cli/util/_LoggingArgumentParser.py
src/wai/common/cli/util/__init__.py
src/wai/common/cli/util/_cli_string.py
src/wai/common/cli/util/_flags.py
src/wai/common/cli/util/_get_option_sub_list.py
src/wai_common.egg-info/PKG-INFO
src/wai_common.egg-info/SOURCES.txt
src/wai_common.egg-info/dependency_links.txt
src/wai_common.egg-info/namespace_packages.txt
src/wai_common.egg-info/requires.txt
src/wai_common.egg-info/top_level.txt
