Metadata-Version: 2.1
Name: wai-common
Version: 0.0.45
Summary: Python library with common functionality for other Waikato projects.
Home-page: https://github.com/waikato-datamining/wai-common
Author: Corey Sterling
Author-email: coreytsterling@gmail.com
License: MIT
Classifier: Development Status :: 4 - Beta
Classifier: License :: OSI Approved :: MIT License
Classifier: Topic :: Scientific/Engineering :: Mathematics
Classifier: Programming Language :: Python :: 3
License-File: LICENSE
